eegcanon/__init__.py
eegcanon/pipeline.py
eegcanon/core/canonical.py
eegcanon/core/epoching.py
eegcanon/core/policy.py
eegcanon/core/warnings.py
eegcanon/features/bandpower.py
eegcanon/features/extract.py
eegcanon/features/hjorth.py
eegcanon/features/psd.py
eegcanon/infer/channels.py
eegcanon/infer/montage.py
eegcanon/infer/sampling.py
eegcanon/io/load_csv.py
eegcanon/io/load_edf.py
eegcanon/io/load_file.py
eegcanon/io/registry.py
eegcanon/normalize/time.py
eegcanon/torch/dataset.py
eegcanon/torch/supervised.py
eegcanon_ml-0.1.2.dist-info/METADATA
eegcanon_ml-0.1.2.dist-info/WHEEL
eegcanon_ml-0.1.2.dist-info/top_level.txt
eegcanon_ml-0.1.2.dist-info/RECORD
