Metadata-Version: 2.4
Name: eegcanon-ml
Version: 0.1.2
Summary: Canonical EEG representation framework
Author: AdhiAlpha27
License: MIT
Project-URL: Homepage, https://github.com/AlphaAdhi27/eegcanon
Project-URL: Repository, https://github.com/AlphaAdhi27/eegcanon
Project-URL: Issues, https://github.com/AlphaAdhi27/eegcanon/issues
Requires-Python: >=3.9
Requires-Dist: numpy
Requires-Dist: scipy
Requires-Dist: pandas
Requires-Dist: mne
Requires-Dist: pydantic
